{"url": "https://downloads.sourceforge.net/project/syberiaos/natrium/syberia_natrium-v2.0-20181123-2149-OFFICIAL.zip?r=https%3A%2F%2Fsourceforge.net%2Fprojects%2Fsyberiaos%2Ffiles%2Fnatrium%2Fsyberia_natrium-v2.0-20181123-2149-OFFICIAL.zip%2Fdownload&ts=1543049076natrium/syberia_natrium-v2.0-20181123-2149-OFFICIAL.zip", "filesize": "560055920", "addons": [{"url": "\"http://tiny.cc/latestmagisk", "summary": "Magisk", "title": "Magisk"}, {"url": "http://tiny.cc/latestuninstaller", "summary": "Magisk Uninstaller", "title": "Magisk"}], "developer_url": "http://github.com/syberia-project", "changelog": "Fixed sensors\n", "device_model": "Mi 5s Plus", "device": "natrium", "md5": "108c48db8dff298e2867eccbd3f4666a", "news_url": "http://github.com/syberia-project", "device_brand": "Xiaomi", "build_date": "20181123", "developer": "cfdddd", "forum_url": "https://forum.xda-developers.com/mi-5s-plus/development/rom-syberia-project-t3869145", "error": "false", "donate_url": "https://syberiaos.com/links", "filename": "syberia_natrium-v2.0-20181123-2149-OFFICIAL.zip", "website_url": "http://syberiaos.com"}