{
  "response": [
    {
      "datetime": 1653560662,
      "filename": "syberia_alioth-v5.4-20220526-1026-OFFICIAL.zip",
      "id": "36adb25a463d87d3f41553074caea53975829207e40e788065805e914f1bcf02",
      "romtype": "OFFICIAL",
      "size": "1140067127",
      "url": "https://sourceforge.net/projects/syberiaos/files/alioth/syberia_alioth-v5.4-20220526-1026-OFFICIAL.zip/download",
      "version": "v5.4",
      "device_brand": "Xiaomi",
      "device_model": "Poco F3",
      "device_codename": "alioth",
      "developer": "DennySPb"
    }
  ]
}