{
  "response": [
    {
      "datetime": 1556965560,
      "filename": "syberia_jasmine_sprout-v2.4-20190504-1026-OFFICIAL.zip",
      "id": "bb255f8d82df713b4972f5c8b3dce36e211a36f713e59aea22de7d23920cc3c4",
      "romtype": "OFFICIAL",
      "size": "750623716",
      "url": "https://sourceforge.net/projects/syberiaos/files/jasmine_sprout/syberia_jasmine_sprout-v2.4-20190504-1026-OFFICIAL.zip/download",
      "version": "v2.4",
      "device_brand": "Xiaomi",
      "device_model": "Mi A2",
      "device_codename": "jasmine_sprout",
      "developer": "coderzstas"
    }
  ]
}