{
  "response": [
    {
      "datetime": 1584205260,
      "filename": "syberia_laurel_sprout-v3.5-20200314-1701-OFFICIAL.zip",
      "id": "b0db3d506057afc14bc7408e5498024cf0d9858ae8ff6b1e4c20f1119c07e932",
      "romtype": "OFFICIAL",
      "size": "654304331",
      "url": "https://sourceforge.net/projects/syberiaos/files/laurel_sprout/syberia_laurel_sprout-v3.5-20200314-1701-OFFICIAL.zip/download",
      "version": "v3.5",
      "device_brand": "Xiaomi",
      "device_model": "Mi A3",
      "device_codename": "laurel_sprout",
      "developer": "HarukeyUA"
    }
  ]
}